StocksMA/StocksMA.py
StocksMA/__init__.py
StocksMA/utils.py
StocksMA-0.1.0.dist-info/LICENSE
StocksMA-0.1.0.dist-info/METADATA
StocksMA-0.1.0.dist-info/WHEEL
StocksMA-0.1.0.dist-info/top_level.txt
StocksMA-0.1.0.dist-info/RECORD
