Metadata-Version: 2.1
Name: StocksMA
Version: 0.1.0
Summary: Retrieve data related to Moroccan stocks from diffrent sources
Home-page: https://github.com/s0v1x/StocksMA
Author: sovix
Author-email: sed.labiad@gmail.com
License: MIT
Project-URL: Bug Tracker, https://github.com/s0v1x/StocksMA/issues
Keywords: pandas,stocks,finance,morocco,ma,yahoo finance,marketwatch,wsj,data,timeseries
Platform: UNKNOWN
Classifier: Programming Language :: Python :: 3
Classifier: License :: OSI Approved :: MIT License
Classifier: Operating System :: OS Independent
Requires-Python: >=3.6
License-File: LICENSE
Requires-Dist: numpy
Requires-Dist: pandas
Requires-Dist: requests
Requires-Dist: beautifulsoup4
Requires-Dist: lxml
Requires-Dist: types-requests
Requires-Dist: types-python-dateutil
